acdh_django_widgets/__init__.py
acdh_django_widgets/widgets.py
acdh_django_widgets/templates/acdh_django_widgets/range_datepicker_widget.html
acdh_django_widgets/templates/acdh_django_widgets/range_one_line.html
acdh_django_widgets/templates/acdh_django_widgets/range_slider_widget.html
acdh_django_widgets-0.1.0.dist-info/LICENSE
acdh_django_widgets-0.1.0.dist-info/METADATA
acdh_django_widgets-0.1.0.dist-info/WHEEL
acdh_django_widgets-0.1.0.dist-info/top_level.txt
acdh_django_widgets-0.1.0.dist-info/RECORD
