Metadata-Version: 2.2
Name: acdh-django-widgets
Version: 0.1.0
Summary: custom widgets for Django-Forms/Filter
Author-email: Peter Andorfer <p.andorfer@gmail.com>
License: MIT License
Requires-Python: >=3.11
License-File: LICENSE
Requires-Dist: django>=5
Requires-Dist: django-filter
